pypec/Analyse_PEC.py
pypec/DotViewer.py
pypec/Parallel_Process.py
pypec/__init__.py
pypec/__main__.py
pypec/icon.png
pypec/iph_functions.py
pypec/plotstyle.py
pypec/version.py
sphinx/source/conf.py
pypec-0.1.1.dist-info/LICENSE.txt
pypec-0.1.1.dist-info/METADATA
pypec-0.1.1.dist-info/WHEEL
pypec-0.1.1.dist-info/top_level.txt
pypec-0.1.1.dist-info/RECORD
