Metadata-Version: 2.1
Name: pypec
Version: 0.1.1
Summary: pypec: photoelectrochemistry for Python.
Author-email: Milan Skocic <milan.skocic@icloud.com>
License: GNU General Public License v3 (GPLv3)
Project-URL: Documentation, https://milanskocic.github.io/pypec/index.html
Project-URL: Source, https://github.com/MilanSkocic/pypec
Classifier: Development Status :: 5 - Production/Stable
Classifier: Intended Audience :: Science/Research
Classifier: Topic :: Scientific/Engineering
Classifier: License :: OSI Approved :: GNU General Public License v3 (GPLv3)
Requires-Python: >=3.6
License-File: LICENSE.txt
